dynamic_rounding/__init__.py
dynamic_rounding/pandas.py
tests/__init__.py
tests/test_core.py
tests/test_pandas.py
dynamic_rounding-0.1.2.dist-info/METADATA
dynamic_rounding-0.1.2.dist-info/WHEEL
dynamic_rounding-0.1.2.dist-info/top_level.txt
dynamic_rounding-0.1.2.dist-info/RECORD
