Metadata-Version: 2.4
Name: dynamic-rounding
Version: 0.1.2
Summary: Dynamic rounding for readable data - rounds based on order of magnitude
Author: Arie Fisher
License: MIT
Project-URL: Homepage, https://github.com/ArieFisher/dynamic-rounding
Project-URL: Repository, https://github.com/ArieFisher/dynamic-rounding
Project-URL: Documentation, https://github.com/ArieFisher/dynamic-rounding#readme
Keywords: rounding,data,pandas,magnitude,formatting
Classifier: Development Status :: 4 - Beta
Classifier: Intended Audience :: Developers
Classifier: Intended Audience :: Science/Research
Classifier: License :: OSI Approved :: MIT License
Classifier: Programming Language :: Python :: 3
Classifier: Programming Language :: Python :: 3.8
Classifier: Programming Language :: Python :: 3.9
Classifier: Programming Language :: Python :: 3.10
Classifier: Programming Language :: Python :: 3.11
Classifier: Programming Language :: Python :: 3.12
Classifier: Topic :: Scientific/Engineering
Classifier: Topic :: Utilities
Requires-Python: >=3.8
Provides-Extra: pandas
Requires-Dist: pandas>=1.0; extra == "pandas"
Provides-Extra: dev
Requires-Dist: pytest>=7.0; extra == "dev"
Requires-Dist: pandas>=1.0; extra == "dev"
